turbofan/__init__.py
turbofan/command.py
turbofan/database.py
turbofan/files.py
turbofan/fixtures.py
turbofan/project.py
turbofan-0.2.2.dist-info/LICENSE
turbofan-0.2.2.dist-info/METADATA
turbofan-0.2.2.dist-info/WHEEL
turbofan-0.2.2.dist-info/RECORD
