Metadata-Version: 2.1
Name: turbofan
Version: 0.2.2
Summary: Essential Libraries and Tools for Streamlined Development
License: The Unlicence
Author: Luís Miranda
Author-email: luistm@gmail.com
Requires-Python: >=3.9,<4.0
Classifier: License :: Other/Proprietary License
Classifier: Programming Language :: Python :: 3
Classifier: Programming Language :: Python :: 3.9
Classifier: Programming Language :: Python :: 3.10
Classifier: Programming Language :: Python :: 3.11
Classifier: Programming Language :: Python :: 3.12
Requires-Dist: sqlalchemy (>=2.0.30,<3.0.0)
Requires-Dist: toml (>=0.10.2,<0.11.0)
